sdk_api_adas/__init__.py
sdk_api_adas/api.py
sdk_api_adas/data_types.py
sdk_api_adas/drivers.py
sdk_api_adas/events.py
sdk_api_adas-0.1.2.dist-info/licenses/LICENSE
sdk_api_adas-ro/__init__.py
sdk_api_adas-0.1.2.dist-info/METADATA
sdk_api_adas-0.1.2.dist-info/WHEEL
sdk_api_adas-0.1.2.dist-info/top_level.txt
sdk_api_adas-0.1.2.dist-info/RECORD
