Metadata-Version: 2.4
Name: sdk-api-adas
Version: 0.1.2
Summary: SDK para interactuar con la API ADAS protegida por AWS IAM
Home-page: https://github.com/Transportes-Rapido-Ochoa/sdk-api-adas
Author: Jose Luis Salamanca Coy
Author-email: jose.salamanca@softgic.co
Classifier: Programming Language :: Python :: 3
Classifier: License :: OSI Approved :: MIT License
Classifier: Operating System :: OS Independent
Requires-Python: >=3.10
License-File: LICENSE
Requires-Dist: pydantic>=1.10.0
Requires-Dist: boto3>=1.20.0
Requires-Dist: requests>=2.32.3
Requires-Dist: requests_aws4auth
Dynamic: author
Dynamic: author-email
Dynamic: classifier
Dynamic: description
Dynamic: description-content-type
Dynamic: home-page
Dynamic: license-file
Dynamic: requires-dist
Dynamic: requires-python
Dynamic: summary
